LICENSE
MANIFEST.in
README.md
setup.cfg
setup.py
hangar51client/__init__.py
hangar51client.egg-info/PKG-INFO
hangar51client.egg-info/SOURCES.txt
hangar51client.egg-info/dependency_links.txt
hangar51client.egg-info/requires.txt
hangar51client.egg-info/top_level.txt