Metadata-Version: 2.1
Name: hangar51client
Version: 2.1.6
Summary: A client library for calling the Hangar51 API
Home-page: https://getme.co.uk
Author: David Bailey
Author-email: david@getme.co.uk
Maintainer: David Bailey, Anthony Blackshaw
Maintainer-email: david@getme.co.uk, ant@getme.co.uk
License: MIT
Keywords: hangar51
Platform: UNKNOWN
Classifier: Development Status :: 5 - Production/Stable
Classifier: Intended Audience :: Developers
Classifier: License :: OSI Approved :: MIT License
Classifier: Operating System :: MacOS :: MacOS X
Classifier: Operating System :: Microsoft :: Windows
Classifier: Operating System :: POSIX
Classifier: Programming Language :: Python :: 3.4
Classifier: Programming Language :: Python :: 3.5
Provides-Extra: dev
Provides-Extra: test
